aiohanspell/__init__.py
aiohanspell/constants.py
aiohanspell/response.py
aiohanspell/spell_checker.py
py_aiohanspell-1.1.dist-info/LICENSE
py_aiohanspell-1.1.dist-info/METADATA
py_aiohanspell-1.1.dist-info/WHEEL
py_aiohanspell-1.1.dist-info/top_level.txt
py_aiohanspell-1.1.dist-info/RECORD
