Metadata-Version: 2.1
Name: py-aiohanspell
Version: 1.1
Summary: 비동기 한글 맞춤법검사 모듈입니다.
Home-page: https://github.com/spacedev-official/py-aiohanspell
Author: SpaceDEV
Author-email: support@spacedev.space
License: UNKNOWN
Platform: UNKNOWN
Classifier: Development Status :: 5 - Production/Stable
Classifier: Intended Audience :: Education
Classifier: Intended Audience :: End Users/Desktop
Classifier: License :: Freeware
Classifier: Operating System :: POSIX
Classifier: Operating System :: Microsoft :: Windows
Classifier: Operating System :: MacOS :: MacOS X
Classifier: Topic :: Education
Classifier: Programming Language :: Python
Classifier: Programming Language :: Python :: 3.7
Classifier: Programming Language :: Python :: 3.8
Requires-Python: >=3.7
License-File: LICENSE
Requires-Dist: aiohttp
